metadv/__init__.py
metadv/generator.py
metadv/generators/__init__.py
metadv/generators/attribute.py
metadv/generators/base.py
metadv/generators/source.py
metadv/generators/source_target.py
metadv/generators/target.py
metadv/templates/TEMPLATE-REFERENCE.md
metadv/templates/datavault-uk/automate_dv/hub.sql
metadv/templates/datavault-uk/automate_dv/link.sql
metadv/templates/datavault-uk/automate_dv/ma_sat.sql
metadv/templates/datavault-uk/automate_dv/sat.sql
metadv/templates/datavault-uk/automate_dv/stage.sql
metadv/templates/datavault-uk/automate_dv/templates.yml
metadv/templates/dimensional/dimension.sql
metadv/templates/dimensional/fact.sql
metadv/templates/dimensional/templates.yml
metadv/templates/scalefreecom/datavault4dbt/hub.sql
metadv/templates/scalefreecom/datavault4dbt/link.sql
metadv/templates/scalefreecom/datavault4dbt/ma_sat.sql
metadv/templates/scalefreecom/datavault4dbt/sat.sql
metadv/templates/scalefreecom/datavault4dbt/stage.sql
metadv/templates/scalefreecom/datavault4dbt/templates.yml
metadv/validations/__init__.py
metadv/validations/base.py
metadv/validations/column_no_connection.py
metadv/validations/entity_no_description.py
metadv/validations/entity_no_source.py
metadv/validations/relation_missing_entity_sources.py
metadv/validations/source_missing_relation_entities.py
metadv-0.3.0.dist-info/METADATA
metadv-0.3.0.dist-info/WHEEL
metadv-0.3.0.dist-info/entry_points.txt
metadv-0.3.0.dist-info/licenses/LICENSE
metadv-0.3.0.dist-info/RECORD
