Metadata-Version: 2.4
Name: metadv
Version: 0.3.0
Summary: Metadata-Driven Data Vault Generator for dbt
Project-URL: Homepage, https://github.com/data-diving/metadv
Project-URL: Documentation, https://github.com/data-diving/metadv#readme
Project-URL: Repository, https://github.com/data-diving/metadv
Project-URL: Issues, https://github.com/data-diving/metadv/issues
Author: MetaDV Contributors
License-Expression: MIT
License-File: LICENSE
Keywords: automate-dv,data-modeling,data-vault,data-warehouse,datavault,datavault4dbt,dbt,generator,sql
Classifier: Development Status :: 4 - Beta
Classifier: Intended Audience :: Developers
Classifier: License :: OSI Approved :: MIT License
Classifier: Operating System :: OS Independent
Classifier: Programming Language :: Python :: 3
Classifier: Programming Language :: Python :: 3.8
Classifier: Programming Language :: Python :: 3.9
Classifier: Programming Language :: Python :: 3.10
Classifier: Programming Language :: Python :: 3.11
Classifier: Programming Language :: Python :: 3.12
Classifier: Topic :: Database
Classifier: Topic :: Software Development :: Code Generators
Requires-Python: >=3.8
Requires-Dist: pyyaml>=5.0
Provides-Extra: dev
Requires-Dist: black>=24.4.0; extra == 'dev'
Requires-Dist: isort>=5.0; extra == 'dev'
Requires-Dist: mypy>=1.0; extra == 'dev'
Requires-Dist: pytest-cov>=4.0; extra == 'dev'
Requires-Dist: pytest>=7.0; extra == 'dev'
Requires-Dist: types-pyyaml>=6.0; extra == 'dev'
